<?xml version="1.0" encoding="utf-8"?>
<tv>
  <channel id="CCTV5">
    <display-name lang="zh">CCTV5</display-name>
  </channel>
  <programme channel="CCTV5" start="20260120000500 +0800" stop="20260120002000 +0800">
    <title lang="zh">实况录像-荣耀十分 U型场地世界杯云顶站谷爱凌夺冠</title>
  </programme>
  <programme channel="CCTV5" start="20260120002000 +0800" stop="20260120011300 +0800">
    <title lang="zh">实况录像-2026年世界职业拳王争霸赛 1</title>
  </programme>
  <programme channel="CCTV5" start="20260120011300 +0800" stop="20260120023800 +0800">
    <title lang="zh">实况录像-2025年世界田联钻石联赛 苏黎世站 1</title>
  </programme>
  <programme channel="CCTV5" start="20260120023800 +0800" stop="20260120040000 +0800">
    <title lang="zh">实况录像-2025/2026赛季中国男子篮球职业联赛 第11轮 青岛崂山啤酒—深圳马可波罗</title>
  </programme>
  <programme channel="CCTV5" start="20260120040000 +0800" stop="20260120053000 +0800">
    <title lang="zh">国际足球赛场-25-26赛季英超联赛第19轮 利物浦—利兹联</title>
  </programme>
  <programme channel="CCTV5" start="20260120053000 +0800" stop="20260120060000 +0800">
    <title lang="zh">实况录像-2025年射箭世界杯总决赛 1</title>
  </programme>
  <programme channel="CCTV5" start="20260120060000 +0800" stop="20260120063000 +0800">
    <title lang="zh">2025/2026赛季雪车世界杯 意大利科尔蒂纳站-男子钢架雪车</title>
  </programme>
  <programme channel="CCTV5" start="20260120063000 +0800" stop="20260120070000 +0800">
    <title lang="zh">健身动起来</title>
  </programme>
  <programme channel="CCTV5" start="20260120070000 +0800" stop="20260120080000 +0800">
    <title lang="zh">体坛晨报</title>
  </programme>
  <programme channel="CCTV5" start="20260120080000 +0800" stop="20260120120000 +0800">
    <title lang="zh">2026年澳大利亚网球公开赛-第1轮3</title>
  </programme>
  <programme channel="CCTV5" start="20260120120000 +0800" stop="20260120123500 +0800">
    <title lang="zh">体坛快讯</title>
  </programme>
  <programme channel="CCTV5" start="20260120123500 +0800" stop="20260120125000 +0800">
    <title lang="zh">艺术里的奥林匹克(4K)</title>
  </programme>
  <programme channel="CCTV5" start="20260120125000 +0800" stop="20260120151000 +0800">
    <title lang="zh">2026年CMG群众足球邀请赛（湖南永州）-小组赛（黑龙江哈尔滨队-湖南永州队）</title>
  </programme>
  <programme channel="CCTV5" start="20260120151000 +0800" stop="20260120160000 +0800">
    <title lang="zh">实况录像-2026年世界职业拳王争霸赛 1</title>
  </programme>
  <programme channel="CCTV5" start="20260120160000 +0800" stop="20260120170000 +0800">
    <title lang="zh">实况录像-2025/2026赛季自由式滑雪世界杯 美国普莱西德湖站 空中技巧个人 第二站</title>
  </programme>
  <programme channel="CCTV5" start="20260120170000 +0800" stop="20260120180000 +0800">
    <title lang="zh">运动一起赢</title>
  </programme>
  <programme channel="CCTV5" start="20260120180000 +0800" stop="20260120183000 +0800">
    <title lang="zh">体育新闻</title>
  </programme>
  <programme channel="CCTV5" start="20260120183000 +0800" stop="20260120190000 +0800">
    <title lang="zh">2025/2026法国足球甲级联赛-第18轮集锦</title>
  </programme>
  <programme channel="CCTV5" start="20260120190000 +0800" stop="20260120193000 +0800">
    <title lang="zh">实况录像-精品赛事记录-2025/2026跳台滑雪世界杯 德国奥伯斯多夫站 女子大跳台</title>
  </programme>
  <programme channel="CCTV5" start="20260120193000 +0800" stop="20260120213000 +0800">
    <title lang="zh">2025/2026赛季中国男子篮球职业联赛常规赛-第17轮(上海久事 - 北京北汽)</title>
  </programme>
  <programme channel="CCTV5" start="20260120213000 +0800" stop="20260120223500 +0800">
    <title lang="zh">体育世界</title>
  </programme>
  <programme channel="CCTV5" start="20260120223500 +0800" stop="20260120230000 +0800">
    <title lang="zh">实况录像-精品赛事记录 2025/2026赛季速度滑冰世界杯 中国队比赛</title>
  </programme>
  <programme channel="CCTV5" start="20260120230000 +0800" stop="20260120235900 +0800">
    <title lang="zh">2026亚足联U23亚洲杯-半决赛（越南-中国）</title>
  </programme>
  <channel id="CCTV5+">
    <display-name lang="zh">CCTV5+</display-name>
  </channel>
  <programme channel="CCTV5+" start="20260120000500 +0800" stop="20260120002000 +0800">
    <title lang="zh">实况录像-荣耀十分 U型场地世界杯云顶站谷爱凌夺冠</title>
  </programme>
  <programme channel="CCTV5+" start="20260120002000 +0800" stop="20260120011300 +0800">
    <title lang="zh">实况录像-2026年世界职业拳王争霸赛 1</title>
  </programme>
  <programme channel="CCTV5+" start="20260120011300 +0800" stop="20260120023800 +0800">
    <title lang="zh">实况录像-2025年世界田联钻石联赛 苏黎世站 1</title>
  </programme>
  <programme channel="CCTV5+" start="20260120023800 +0800" stop="20260120040000 +0800">
    <title lang="zh">实况录像-2025/2026赛季中国男子篮球职业联赛 第11轮 青岛崂山啤酒—深圳马可波罗</title>
  </programme>
  <programme channel="CCTV5+" start="20260120040000 +0800" stop="20260120053000 +0800">
    <title lang="zh">国际足球赛场-25-26赛季英超联赛第19轮 利物浦—利兹联</title>
  </programme>
  <programme channel="CCTV5+" start="20260120053000 +0800" stop="20260120060000 +0800">
    <title lang="zh">实况录像-2025年射箭世界杯总决赛 1</title>
  </programme>
  <programme channel="CCTV5+" start="20260120060000 +0800" stop="20260120063000 +0800">
    <title lang="zh">2025/2026赛季雪车世界杯 意大利科尔蒂纳站-男子钢架雪车</title>
  </programme>
  <programme channel="CCTV5+" start="20260120063000 +0800" stop="20260120070000 +0800">
    <title lang="zh">健身动起来</title>
  </programme>
  <programme channel="CCTV5+" start="20260120070000 +0800" stop="20260120080000 +0800">
    <title lang="zh">体坛晨报</title>
  </programme>
  <programme channel="CCTV5+" start="20260120080000 +0800" stop="20260120120000 +0800">
    <title lang="zh">2026年澳大利亚网球公开赛-第1轮3</title>
  </programme>
  <programme channel="CCTV5+" start="20260120120000 +0800" stop="20260120123500 +0800">
    <title lang="zh">体坛快讯</title>
  </programme>
  <programme channel="CCTV5+" start="20260120123500 +0800" stop="20260120125000 +0800">
    <title lang="zh">艺术里的奥林匹克(4K)</title>
  </programme>
  <programme channel="CCTV5+" start="20260120125000 +0800" stop="20260120151000 +0800">
    <title lang="zh">2026年CMG群众足球邀请赛（湖南永州）-小组赛（黑龙江哈尔滨队-湖南永州队）</title>
  </programme>
  <programme channel="CCTV5+" start="20260120151000 +0800" stop="20260120160000 +0800">
    <title lang="zh">实况录像-2026年世界职业拳王争霸赛 1</title>
  </programme>
  <programme channel="CCTV5+" start="20260120160000 +0800" stop="20260120170000 +0800">
    <title lang="zh">实况录像-2025/2026赛季自由式滑雪世界杯 美国普莱西德湖站 空中技巧个人 第二站</title>
  </programme>
  <programme channel="CCTV5+" start="20260120170000 +0800" stop="20260120180000 +0800">
    <title lang="zh">运动一起赢</title>
  </programme>
  <programme channel="CCTV5+" start="20260120180000 +0800" stop="20260120183000 +0800">
    <title lang="zh">体育新闻</title>
  </programme>
  <programme channel="CCTV5+" start="20260120183000 +0800" stop="20260120190000 +0800">
    <title lang="zh">2025/2026法国足球甲级联赛-第18轮集锦</title>
  </programme>
  <programme channel="CCTV5+" start="20260120190000 +0800" stop="20260120193000 +0800">
    <title lang="zh">实况录像-精品赛事记录-2025/2026跳台滑雪世界杯 德国奥伯斯多夫站 女子大跳台</title>
  </programme>
  <programme channel="CCTV5+" start="20260120193000 +0800" stop="20260120213000 +0800">
    <title lang="zh">2025/2026赛季中国男子篮球职业联赛常规赛-第17轮(上海久事 - 北京北汽)</title>
  </programme>
  <programme channel="CCTV5+" start="20260120213000 +0800" stop="20260120223500 +0800">
    <title lang="zh">体育世界</title>
  </programme>
  <programme channel="CCTV5+" start="20260120223500 +0800" stop="20260120230000 +0800">
    <title lang="zh">实况录像-精品赛事记录 2025/2026赛季速度滑冰世界杯 中国队比赛</title>
  </programme>
  <programme channel="CCTV5+" start="20260120230000 +0800" stop="20260120235900 +0800">
    <title lang="zh">2026亚足联U23亚洲杯-半决赛（越南-中国）</title>
  </programme>
  <channel id="CHC动作电影">
    <display-name lang="zh">CHC动作电影</display-name>
  </channel>
  <programme channel="CHC动作电影" start="20260120001000 +0800" stop="20260120020000 +0800">
    <title lang="zh">警察故事2013</title>
  </programme>
  <programme channel="CHC动作电影" start="20260120020000 +0800" stop="20260120040000 +0800">
    <title lang="zh">悬崖之上</title>
  </programme>
  <programme channel="CHC动作电影" start="20260120040000 +0800" stop="20260120053000 +0800">
    <title lang="zh">天下第一剑</title>
  </programme>
  <programme channel="CHC动作电影" start="20260120053000 +0800" stop="20260120070000 +0800">
    <title lang="zh">歼十出击</title>
  </programme>
  <programme channel="CHC动作电影" start="20260120070000 +0800" stop="20260120082000 +0800">
    <title lang="zh">少林四小龙</title>
  </programme>
  <programme channel="CHC动作电影" start="20260120082000 +0800" stop="20260120100500 +0800">
    <title lang="zh">绝密档案</title>
  </programme>
  <programme channel="CHC动作电影" start="20260120100500 +0800" stop="20260120114000 +0800">
    <title lang="zh">执笔为刀</title>
  </programme>
  <programme channel="CHC动作电影" start="20260120114000 +0800" stop="20260120131000 +0800">
    <title lang="zh">甲骨文密码</title>
  </programme>
  <programme channel="CHC动作电影" start="20260120131000 +0800" stop="20260120154500 +0800">
    <title lang="zh">荆轲刺秦王</title>
  </programme>
  <programme channel="CHC动作电影" start="20260120154500 +0800" stop="20260120172500 +0800">
    <title lang="zh">少林寺（银都）</title>
  </programme>
  <programme channel="CHC动作电影" start="20260120172500 +0800" stop="20260120190000 +0800">
    <title lang="zh">至尊一剑</title>
  </programme>
  <programme channel="CHC动作电影" start="20260120190000 +0800" stop="20260120203000 +0800">
    <title lang="zh">缉枪行动</title>
  </programme>
  <programme channel="CHC动作电影" start="20260120203000 +0800" stop="20260120232000 +0800">
    <title lang="zh">烈火金钢 (上.下)</title>
  </programme>
  <programme channel="CHC动作电影" start="20260120232000 +0800" stop="20260120235900 +0800">
    <title lang="zh">侏罗纪世界3</title>
  </programme>
  <channel id="CHC家庭影院">
    <display-name lang="zh">CHC家庭影院</display-name>
  </channel>
  <programme channel="CHC家庭影院" start="20260120011500 +0800" stop="20260120025000 +0800">
    <title lang="zh">大闹天竺</title>
  </programme>
  <programme channel="CHC家庭影院" start="20260120025000 +0800" stop="20260120043000 +0800">
    <title lang="zh">超级的我</title>
  </programme>
  <programme channel="CHC家庭影院" start="20260120043000 +0800" stop="20260120060000 +0800">
    <title lang="zh">人间至味</title>
  </programme>
  <programme channel="CHC家庭影院" start="20260120060000 +0800" stop="20260120074000 +0800">
    <title lang="zh">疯狂72小时</title>
  </programme>
  <programme channel="CHC家庭影院" start="20260120074000 +0800" stop="20260120092500 +0800">
    <title lang="zh">无名之辈</title>
  </programme>
  <programme channel="CHC家庭影院" start="20260120092500 +0800" stop="20260120110500 +0800">
    <title lang="zh">卡拉是条狗（上、下）</title>
  </programme>
  <programme channel="CHC家庭影院" start="20260120110500 +0800" stop="20260120132500 +0800">
    <title lang="zh">托米莉斯女王</title>
  </programme>
  <programme channel="CHC家庭影院" start="20260120132500 +0800" stop="20260120151500 +0800">
    <title lang="zh">哈里斯夫人闯巴黎</title>
  </programme>
  <programme channel="CHC家庭影院" start="20260120151500 +0800" stop="20260120165000 +0800">
    <title lang="zh">疯狂元素城</title>
  </programme>
  <programme channel="CHC家庭影院" start="20260120165000 +0800" stop="20260120183000 +0800">
    <title lang="zh">百变爱人</title>
  </programme>
  <programme channel="CHC家庭影院" start="20260120183000 +0800" stop="20260120202000 +0800">
    <title lang="zh">老师·好</title>
  </programme>
  <programme channel="CHC家庭影院" start="20260120202000 +0800" stop="20260120220000 +0800">
    <title lang="zh">找到你</title>
  </programme>
  <programme channel="CHC家庭影院" start="20260120220000 +0800" stop="20260120232500 +0800">
    <title lang="zh">侠客行</title>
  </programme>
  <programme channel="CHC家庭影院" start="20260120232500 +0800" stop="20260120235900 +0800">
    <title lang="zh">破风</title>
  </programme>
  <channel id="CHC影迷电影">
    <display-name lang="zh">CHC影迷电影</display-name>
  </channel>
  <channel id="上海都市">
    <display-name lang="zh">上海都市</display-name>
  </channel>
  <programme channel="上海都市" start="20260120000000 +0800" stop="20260120000700 +0800">
    <title lang="zh">乐活上海（260）</title>
  </programme>
  <programme channel="上海都市" start="20260120000700 +0800" stop="20260120004800 +0800">
    <title lang="zh">X诊所（2344）寒冬腊月进补仪式感</title>
  </programme>
  <programme channel="上海都市" start="20260120004800 +0800" stop="20260120013900 +0800">
    <title lang="zh">新老娘舅（5151）</title>
  </programme>
  <programme channel="上海都市" start="20260120013900 +0800" stop="20260120060000 +0800">
    <title lang="zh">祝您晚安</title>
  </programme>
  <programme channel="上海都市" start="20260120060000 +0800" stop="20260120070100 +0800">
    <title lang="zh">新老娘舅（5151）</title>
  </programme>
  <programme channel="上海都市" start="20260120070100 +0800" stop="20260120072700 +0800">
    <title lang="zh">人气美食（4991）</title>
  </programme>
  <programme channel="上海都市" start="20260120072700 +0800" stop="20260120075300 +0800">
    <title lang="zh">乐活上海（259）</title>
  </programme>
  <programme channel="上海都市" start="20260120075300 +0800" stop="20260120083300 +0800">
    <title lang="zh">X诊所（2343）冬季防烫伤指南</title>
  </programme>
  <programme channel="上海都市" start="20260120083300 +0800" stop="20260120085800 +0800">
    <title lang="zh">人气美食（4995）</title>
  </programme>
  <programme channel="上海都市" start="20260120085800 +0800" stop="20260120092300 +0800">
    <title lang="zh">乐活上海（260）</title>
  </programme>
  <programme channel="上海都市" start="20260120092300 +0800" stop="20260120095100 +0800">
    <title lang="zh">开心全接触－我们退休啦（2602）</title>
  </programme>
  <programme channel="上海都市" start="20260120095100 +0800" stop="20260120101300 +0800">
    <title lang="zh">开心全接触－极智装（1393）</title>
  </programme>
  <programme channel="上海都市" start="20260120101300 +0800" stop="20260120110700 +0800">
    <title lang="zh">新老娘舅（5151）</title>
  </programme>
  <programme channel="上海都市" start="20260120110700 +0800" stop="20260120112300 +0800">
    <title lang="zh">都市焕新家（82）</title>
  </programme>
  <programme channel="上海都市" start="20260120112300 +0800" stop="20260120114200 +0800">
    <title lang="zh">36．7℃（23）</title>
  </programme>
  <programme channel="上海都市" start="20260120114200 +0800" stop="20260120125300 +0800">
    <title lang="zh">纪录片真实影院（286）　籍籍无名6：苏文源天天开心</title>
  </programme>
  <programme channel="上海都市" start="20260120125300 +0800" stop="20260120133500 +0800">
    <title lang="zh">X诊所（2344）寒冬腊月进补仪式感</title>
  </programme>
  <programme channel="上海都市" start="20260120133500 +0800" stop="20260120140100 +0800">
    <title lang="zh">乐活上海（260）</title>
  </programme>
  <programme channel="上海都市" start="20260120140100 +0800" stop="20260120144200 +0800">
    <title lang="zh">46集连续剧：甜蜜（31）</title>
  </programme>
  <programme channel="上海都市" start="20260120144200 +0800" stop="20260120152400 +0800">
    <title lang="zh">46集连续剧：甜蜜（32）</title>
  </programme>
  <programme channel="上海都市" start="20260120152400 +0800" stop="20260120161900 +0800">
    <title lang="zh">新老娘舅（5151）</title>
  </programme>
  <programme channel="上海都市" start="20260120161900 +0800" stop="20260120163700 +0800">
    <title lang="zh">人气美食（4991）</title>
  </programme>
  <programme channel="上海都市" start="20260120163700 +0800" stop="20260120170900 +0800">
    <title lang="zh">乐活上海（260）</title>
  </programme>
  <programme channel="上海都市" start="20260120170900 +0800" stop="20260120173000 +0800">
    <title lang="zh">开心全接触－极智装（1394）</title>
  </programme>
  <programme channel="上海都市" start="20260120173000 +0800" stop="20260120175700 +0800">
    <title lang="zh">开心全接触－淘最上海（4059）</title>
  </programme>
  <programme channel="上海都市" start="20260120175700 +0800" stop="20260120190000 +0800">
    <title lang="zh">新老娘舅（5152）　老三究竟有没有阻挠母亲立遗嘱？</title>
  </programme>
  <programme channel="上海都市" start="20260120190000 +0800" stop="20260120192900 +0800">
    <title lang="zh">乐活上海（261）</title>
  </programme>
  <programme channel="上海都市" start="20260120192900 +0800" stop="20260120195500 +0800">
    <title lang="zh">人气美食（4996）</title>
  </programme>
  <programme channel="上海都市" start="20260120195500 +0800" stop="20260120200400 +0800">
    <title lang="zh">都市圈＠SMG达人和朋友们（52）</title>
  </programme>
  <programme channel="上海都市" start="20260120200400 +0800" stop="20260120203000 +0800">
    <title lang="zh">乐活上海</title>
  </programme>
  <programme channel="上海都市" start="20260120203000 +0800" stop="20260120205600 +0800">
    <title lang="zh">人气美食（4992）</title>
  </programme>
  <programme channel="上海都市" start="20260120205600 +0800" stop="20260120214300 +0800">
    <title lang="zh">X诊所（2345）大寒节气养生</title>
  </programme>
  <programme channel="上海都市" start="20260120214300 +0800" stop="20260120221700 +0800">
    <title lang="zh">纪录片真实影院（287）　万桥飞架1</title>
  </programme>
  <programme channel="上海都市" start="20260120221700 +0800" stop="20260120223800 +0800">
    <title lang="zh">开心全接触－极智装（1394）</title>
  </programme>
  <programme channel="上海都市" start="20260120223800 +0800" stop="20260120230300 +0800">
    <title lang="zh">人气美食（4996）</title>
  </programme>
  <programme channel="上海都市" start="20260120230300 +0800" stop="20260120232700 +0800">
    <title lang="zh">乐活上海（261）</title>
  </programme>
  <programme channel="上海都市" start="20260120232700 +0800" stop="20260120235900 +0800">
    <title lang="zh">X诊所（2345）大寒节气养生</title>
  </programme>
  <channel id="上视新闻">
    <display-name lang="zh">上视新闻</display-name>
  </channel>
  <channel id="东方卫视">
    <display-name lang="zh">东方卫视</display-name>
  </channel>
  <programme channel="东方卫视" start="20260120000000 +0800" stop="20260120000300 +0800">
    <title lang="zh">总局公益展播纪录片：熊猫奇遇记　第一季（3）山林呼唤</title>
  </programme>
  <programme channel="东方卫视" start="20260120000300 +0800" stop="20260120004400 +0800">
    <title lang="zh">电视连续剧：《后浪》（14）</title>
  </programme>
  <programme channel="东方卫视" start="20260120004400 +0800" stop="20260120012500 +0800">
    <title lang="zh">电视连续剧：《后浪》（15）</title>
  </programme>
  <programme channel="东方卫视" start="20260120012500 +0800" stop="20260120020000 +0800">
    <title lang="zh">电视连续剧：《后浪》（16）</title>
  </programme>
  <programme channel="东方卫视" start="20260120020000 +0800" stop="20260120060100 +0800">
    <title lang="zh">祝您晚安</title>
  </programme>
  <programme channel="东方卫视" start="20260120060100 +0800" stop="20260120064200 +0800">
    <title lang="zh">电视连续剧：《后浪》（17）</title>
  </programme>
  <programme channel="东方卫视" start="20260120064200 +0800" stop="20260120070000 +0800">
    <title lang="zh">电视连续剧：《后浪》（18）上</title>
  </programme>
  <programme channel="东方卫视" start="20260120070000 +0800" stop="20260120085900 +0800">
    <title lang="zh">中华人民共和国国歌＋看东方</title>
  </programme>
  <programme channel="东方卫视" start="20260120085900 +0800" stop="20260120090200 +0800">
    <title lang="zh">天气预报</title>
  </programme>
  <programme channel="东方卫视" start="20260120090200 +0800" stop="20260120094600 +0800">
    <title lang="zh">电视连续剧：《大生意人》（23）</title>
  </programme>
  <programme channel="东方卫视" start="20260120094600 +0800" stop="20260120103000 +0800">
    <title lang="zh">电视连续剧：《大生意人》（24）</title>
  </programme>
  <programme channel="东方卫视" start="20260120103000 +0800" stop="20260120111400 +0800">
    <title lang="zh">电视连续剧：《大生意人》（25）</title>
  </programme>
  <programme channel="东方卫视" start="20260120111400 +0800" stop="20260120120000 +0800">
    <title lang="zh">电视连续剧：《大生意人》（26）</title>
  </programme>
  <programme channel="东方卫视" start="20260120120000 +0800" stop="20260120122600 +0800">
    <title lang="zh">午间30分</title>
  </programme>
  <programme channel="东方卫视" start="20260120122600 +0800" stop="20260120123000 +0800">
    <title lang="zh">天气预报</title>
  </programme>
  <programme channel="东方卫视" start="20260120123000 +0800" stop="20260120124300 +0800">
    <title lang="zh">ShanghaiEye</title>
  </programme>
  <programme channel="东方卫视" start="20260120124300 +0800" stop="20260120132500 +0800">
    <title lang="zh">电视连续剧：《以家人之名》（25）</title>
  </programme>
  <programme channel="东方卫视" start="20260120132500 +0800" stop="20260120140600 +0800">
    <title lang="zh">电视连续剧：《以家人之名》（26）</title>
  </programme>
  <programme channel="东方卫视" start="20260120140600 +0800" stop="20260120144700 +0800">
    <title lang="zh">电视连续剧：《以家人之名》（27）</title>
  </programme>
  <programme channel="东方卫视" start="20260120144700 +0800" stop="20260120152800 +0800">
    <title lang="zh">电视连续剧：《以家人之名》（28）</title>
  </programme>
  <programme channel="东方卫视" start="20260120152800 +0800" stop="20260120160700 +0800">
    <title lang="zh">电视连续剧：《以家人之名》（29）</title>
  </programme>
  <programme channel="东方卫视" start="20260120160700 +0800" stop="20260120164600 +0800">
    <title lang="zh">电视连续剧：《以家人之名》（30）</title>
  </programme>
  <programme channel="东方卫视" start="20260120164600 +0800" stop="20260120170600 +0800">
    <title lang="zh">电视连续剧：《以家人之名》（31）上</title>
  </programme>
  <programme channel="东方卫视" start="20260120170600 +0800" stop="20260120173300 +0800">
    <title lang="zh">东方新娱乐</title>
  </programme>
  <programme channel="东方卫视" start="20260120173300 +0800" stop="20260120180000 +0800">
    <title lang="zh">《名医话养生》（122）</title>
  </programme>
  <programme channel="东方卫视" start="20260120180000 +0800" stop="20260120185700 +0800">
    <title lang="zh">东方新闻</title>
  </programme>
  <programme channel="东方卫视" start="20260120185700 +0800" stop="20260120190000 +0800">
    <title lang="zh">天气预报</title>
  </programme>
  <programme channel="东方卫视" start="20260120190000 +0800" stop="20260120193200 +0800">
    <title lang="zh">转（中央台）新闻联播</title>
  </programme>
  <programme channel="东方卫视" start="20260120193200 +0800" stop="20260120201600 +0800">
    <title lang="zh">电视连续剧：《轧戏》（19）</title>
  </programme>
  <programme channel="东方卫视" start="20260120201600 +0800" stop="20260120210100 +0800">
    <title lang="zh">电视连续剧：《轧戏》（20）</title>
  </programme>
  <programme channel="东方卫视" start="20260120210100 +0800" stop="20260120210600 +0800">
    <title lang="zh">东方看大剧</title>
  </programme>
  <programme channel="东方卫视" start="20260120210600 +0800" stop="20260120212000 +0800">
    <title lang="zh">品质东方微剧场－《马背摇篮》（10）</title>
  </programme>
  <programme channel="东方卫视" start="20260120212000 +0800" stop="20260120215900 +0800">
    <title lang="zh">今晚</title>
  </programme>
  <programme channel="东方卫视" start="20260120215900 +0800" stop="20260120220000 +0800">
    <title lang="zh">天气预报</title>
  </programme>
  <programme channel="东方卫视" start="20260120220000 +0800" stop="20260120225000 +0800">
    <title lang="zh">纪录片：动物王国（3）</title>
  </programme>
  <programme channel="东方卫视" start="20260120225000 +0800" stop="20260120225400 +0800">
    <title lang="zh">纪录片：述说（4）</title>
  </programme>
  <programme channel="东方卫视" start="20260120225400 +0800" stop="20260120235900 +0800">
    <title lang="zh">总局公益展播纪录片：熊猫奇遇记　第一季（4）归林逐梦</title>
  </programme>
  <channel id="东方影视">
    <display-name lang="zh">东方影视</display-name>
  </channel>
  <channel id="乐游">
    <display-name lang="zh">乐游</display-name>
  </channel>
  <programme channel="乐游" start="20260120000000 +0800" stop="20260120004100 +0800">
    <title lang="zh">行走的博物馆:古币常存不计春</title>
  </programme>
  <programme channel="乐游" start="20260120004100 +0800" stop="20260120010800 +0800">
    <title lang="zh">马背之旅(101):佛蒙特州</title>
  </programme>
  <programme channel="乐游" start="20260120010800 +0800" stop="20260120013000 +0800">
    <title lang="zh">寻找黔味2(2)</title>
  </programme>
  <programme channel="乐游" start="20260120013000 +0800" stop="20260120020500 +0800">
    <title lang="zh">川味3(3):百废作馔</title>
  </programme>
  <programme channel="乐游" start="20260120020500 +0800" stop="20260120024800 +0800">
    <title lang="zh">行走的博物馆(7):竞夜百戏妙趣生</title>
  </programme>
  <programme channel="乐游" start="20260120024800 +0800" stop="20260120032500 +0800">
    <title lang="zh">大河之北1(1):得名河北</title>
  </programme>
  <programme channel="乐游" start="20260120032500 +0800" stop="20260120033300 +0800">
    <title lang="zh">长城我们的故事(9):法理之内</title>
  </programme>
  <programme channel="乐游" start="20260120033300 +0800" stop="20260120035700 +0800">
    <title lang="zh">记录冬日(1)</title>
  </programme>
  <programme channel="乐游" start="20260120035700 +0800" stop="20260120040200 +0800">
    <title lang="zh">乐游虹口:虹口三章</title>
  </programme>
  <programme channel="乐游" start="20260120040200 +0800" stop="20260120042200 +0800">
    <title lang="zh">寻找黔味2(3)</title>
  </programme>
  <programme channel="乐游" start="20260120042200 +0800" stop="20260120042400 +0800">
    <title lang="zh">一碗人间烟火:茶香花椒清酒焗蟹</title>
  </programme>
  <programme channel="乐游" start="20260120042400 +0800" stop="20260120045900 +0800">
    <title lang="zh">川味3(4):天赐神器</title>
  </programme>
  <programme channel="乐游" start="20260120045900 +0800" stop="20260120054000 +0800">
    <title lang="zh">行走的博物馆(8):无限江山一凭栏</title>
  </programme>
  <programme channel="乐游" start="20260120054000 +0800" stop="20260120061900 +0800">
    <title lang="zh">大河之北1(2):燕赵脊梁</title>
  </programme>
  <programme channel="乐游" start="20260120061900 +0800" stop="20260120062500 +0800">
    <title lang="zh">长城我们的故事(11):虚实之间</title>
  </programme>
  <programme channel="乐游" start="20260120062500 +0800" stop="20260120063100 +0800">
    <title lang="zh">城市推荐官(24):普陀新三样</title>
  </programme>
  <programme channel="乐游" start="20260120063100 +0800" stop="20260120065600 +0800">
    <title lang="zh">记录冬日(2)</title>
  </programme>
  <programme channel="乐游" start="20260120065600 +0800" stop="20260120070000 +0800">
    <title lang="zh">乐游徐汇:徐汇非遗之旅</title>
  </programme>
  <programme channel="乐游" start="20260120070000 +0800" stop="20260120072000 +0800">
    <title lang="zh">寻找黔味2(4)</title>
  </programme>
  <programme channel="乐游" start="20260120072000 +0800" stop="20260120072300 +0800">
    <title lang="zh">一碗人间烟火:春菜烩小黄鱼卷</title>
  </programme>
  <programme channel="乐游" start="20260120072300 +0800" stop="20260120075800 +0800">
    <title lang="zh">川味3(5):化作鲜美</title>
  </programme>
  <programme channel="乐游" start="20260120075800 +0800" stop="20260120075900 +0800">
    <title lang="zh">荧屏之星新春版(1)</title>
  </programme>
  <programme channel="乐游" start="20260120075900 +0800" stop="20260120084200 +0800">
    <title lang="zh">行走的博物馆(9):但愿世间人无病</title>
  </programme>
  <programme channel="乐游" start="20260120084200 +0800" stop="20260120092100 +0800">
    <title lang="zh">大河之北1(3):广袤高原</title>
  </programme>
  <programme channel="乐游" start="20260120092100 +0800" stop="20260120092700 +0800">
    <title lang="zh">长城我们的故事:长城保护(20)</title>
  </programme>
  <programme channel="乐游" start="20260120092700 +0800" stop="20260120093300 +0800">
    <title lang="zh">城市推荐官(25):松江非遗美食</title>
  </programme>
  <programme channel="乐游" start="20260120093300 +0800" stop="20260120095800 +0800">
    <title lang="zh">记录冬日(3)</title>
  </programme>
  <programme channel="乐游" start="20260120095800 +0800" stop="20260120102800 +0800">
    <title lang="zh">发现新上海5(2):读懂建筑</title>
  </programme>
  <programme channel="乐游" start="20260120102800 +0800" stop="20260120103000 +0800">
    <title lang="zh">一碗人间烟火:春笋年糕白鲳鱼</title>
  </programme>
  <programme channel="乐游" start="20260120103000 +0800" stop="20260120104500 +0800">
    <title lang="zh">川味1(7):豆瓣</title>
  </programme>
  <programme channel="乐游" start="20260120104500 +0800" stop="20260120104600 +0800">
    <title lang="zh">荧屏之星新春版(1)</title>
  </programme>
  <programme channel="乐游" start="20260120104600 +0800" stop="20260120105600 +0800">
    <title lang="zh">四季上海</title>
  </programme>
  <programme channel="乐游" start="20260120105600 +0800" stop="20260120113800 +0800">
    <title lang="zh">行走的博物馆:温润以泽君子风</title>
  </programme>
  <programme channel="乐游" start="20260120113800 +0800" stop="20260120121600 +0800">
    <title lang="zh">大河之北1(4):沃野千里</title>
  </programme>
  <programme channel="乐游" start="20260120121600 +0800" stop="20260120122400 +0800">
    <title lang="zh">长城我们的故事(13):长城之恋</title>
  </programme>
  <programme channel="乐游" start="20260120122400 +0800" stop="20260120122900 +0800">
    <title lang="zh">城市推荐官(26):漫步普陀</title>
  </programme>
  <programme channel="乐游" start="20260120122900 +0800" stop="20260120125300 +0800">
    <title lang="zh">记录冬日(4)</title>
  </programme>
  <programme channel="乐游" start="20260120125300 +0800" stop="20260120125800 +0800">
    <title lang="zh">乐游上海:我的黄浦攻略</title>
  </programme>
  <programme channel="乐游" start="20260120125800 +0800" stop="20260120132700 +0800">
    <title lang="zh">发现新上海5(1):浦江之滨</title>
  </programme>
  <programme channel="乐游" start="20260120132700 +0800" stop="20260120132900 +0800">
    <title lang="zh">一碗人间烟火:奶茶新西兰青口贝</title>
  </programme>
  <programme channel="乐游" start="20260120132900 +0800" stop="20260120135600 +0800">
    <title lang="zh">发现新上海:魔都早餐(1)</title>
  </programme>
  <programme channel="乐游" start="20260120135600 +0800" stop="20260120135700 +0800">
    <title lang="zh">荧屏之星新春版(1)</title>
  </programme>
  <programme channel="乐游" start="20260120135700 +0800" stop="20260120144000 +0800">
    <title lang="zh">行走的博物馆:野蛮体魄长精神</title>
  </programme>
  <programme channel="乐游" start="20260120144000 +0800" stop="20260120151900 +0800">
    <title lang="zh">大河之北1(5):向水而居</title>
  </programme>
  <programme channel="乐游" start="20260120151900 +0800" stop="20260120152500 +0800">
    <title lang="zh">长城我们的故事:老长城的新主播</title>
  </programme>
  <programme channel="乐游" start="20260120152500 +0800" stop="20260120153100 +0800">
    <title lang="zh">城市推荐官(27):普陀非遗美食</title>
  </programme>
  <programme channel="乐游" start="20260120153100 +0800" stop="20260120155500 +0800">
    <title lang="zh">记录冬日(5)</title>
  </programme>
  <programme channel="乐游" start="20260120155500 +0800" stop="20260120155800 +0800">
    <title lang="zh">乐游上海:书香文化淮海路</title>
  </programme>
  <programme channel="乐游" start="20260120155800 +0800" stop="20260120162500 +0800">
    <title lang="zh">湘当韵味2(1):水韵边城</title>
  </programme>
  <programme channel="乐游" start="20260120162500 +0800" stop="20260120170000 +0800">
    <title lang="zh">川味3(6):油燃而生</title>
  </programme>
  <programme channel="乐游" start="20260120170000 +0800" stop="20260120174100 +0800">
    <title lang="zh">行走的博物馆:古币常存不计春</title>
  </programme>
  <programme channel="乐游" start="20260120174100 +0800" stop="20260120182000 +0800">
    <title lang="zh">大河之北1(6):面朝大海</title>
  </programme>
  <programme channel="乐游" start="20260120182000 +0800" stop="20260120182700 +0800">
    <title lang="zh">长城我们的故事(15)</title>
  </programme>
  <programme channel="乐游" start="20260120182700 +0800" stop="20260120183200 +0800">
    <title lang="zh">城市推荐官:苏州河百年工业文明</title>
  </programme>
  <programme channel="乐游" start="20260120183200 +0800" stop="20260120185900 +0800">
    <title lang="zh">马背之旅(101):佛蒙特州</title>
  </programme>
  <programme channel="乐游" start="20260120185900 +0800" stop="20260120190000 +0800">
    <title lang="zh">乐游黄浦:乐动西藏路</title>
  </programme>
  <programme channel="乐游" start="20260120190000 +0800" stop="20260120192500 +0800">
    <title lang="zh">湘当韵味2(2):雄山奇味</title>
  </programme>
  <programme channel="乐游" start="20260120192500 +0800" stop="20260120200200 +0800">
    <title lang="zh">万物滋养2(1):森林的芳香</title>
  </programme>
  <programme channel="乐游" start="20260120200200 +0800" stop="20260120204500 +0800">
    <title lang="zh">行走的博物馆:隽永留痕见智心</title>
  </programme>
  <programme channel="乐游" start="20260120204500 +0800" stop="20260120210900 +0800">
    <title lang="zh">美丽乡村(1):天之涯</title>
  </programme>
  <programme channel="乐游" start="20260120210900 +0800" stop="20260120212700 +0800">
    <title lang="zh">喀斯特地貌的历史记忆:八音灵韵</title>
  </programme>
  <programme channel="乐游" start="20260120212700 +0800" stop="20260120213100 +0800">
    <title lang="zh">城市推荐官(29):剧本杀</title>
  </programme>
  <programme channel="乐游" start="20260120213100 +0800" stop="20260120215800 +0800">
    <title lang="zh">马背之旅(102):卡罗莱纳</title>
  </programme>
  <programme channel="乐游" start="20260120215800 +0800" stop="20260120222300 +0800">
    <title lang="zh">湘当韵味2(2):雄山奇味</title>
  </programme>
  <programme channel="乐游" start="20260120222300 +0800" stop="20260120225900 +0800">
    <title lang="zh">万物滋养2(1):森林的芳香</title>
  </programme>
  <programme channel="乐游" start="20260120225900 +0800" stop="20260120232300 +0800">
    <title lang="zh">美丽乡村(1):天之涯</title>
  </programme>
  <programme channel="乐游" start="20260120232300 +0800" stop="20260120234100 +0800">
    <title lang="zh">喀斯特地貌的历史记忆:八音灵韵</title>
  </programme>
  <programme channel="乐游" start="20260120234100 +0800" stop="20260120235900 +0800">
    <title lang="zh">喀斯特地貌的历史记忆:水族密语</title>
  </programme>
  <channel id="五星体育">
    <display-name lang="zh">五星体育</display-name>
  </channel>
  <programme channel="五星体育" start="20260120004900 +0800" stop="20260120060400 +0800">
    <title lang="zh">2025-26赛季NBA常规赛:湖人-雄鹿</title>
  </programme>
  <programme channel="五星体育" start="20260120060400 +0800" stop="20260120063000 +0800">
    <title lang="zh">2025极速终点线11</title>
  </programme>
  <programme channel="五星体育" start="20260120063000 +0800" stop="20260120072700 +0800">
    <title lang="zh">2025年沃尔沃 中国公开赛 决赛</title>
  </programme>
  <programme channel="五星体育" start="20260120072700 +0800" stop="20260120130100 +0800">
    <title lang="zh">2025 中国壁球公开赛 男单半决赛1</title>
  </programme>
  <programme channel="五星体育" start="20260120130100 +0800" stop="20260120133100 +0800">
    <title lang="zh">棋牌新教室</title>
  </programme>
  <programme channel="五星体育" start="20260120133100 +0800" stop="20260120140100 +0800">
    <title lang="zh">第十五届 全国运动会 拳击决赛</title>
  </programme>
  <programme channel="五星体育" start="20260120140100 +0800" stop="20260120140600 +0800">
    <title lang="zh">健身时代 精选周二</title>
  </programme>
  <programme channel="五星体育" start="20260120140600 +0800" stop="20260120150500 +0800">
    <title lang="zh">2025第十五届 全运会 女子双人10米跳台决赛</title>
  </programme>
  <programme channel="五星体育" start="20260120150500 +0800" stop="20260120155500 +0800">
    <title lang="zh">2025 波士顿马拉松</title>
  </programme>
  <programme channel="五星体育" start="20260120155500 +0800" stop="20260120160000 +0800">
    <title lang="zh">健身时代 精选周二</title>
  </programme>
  <programme channel="五星体育" start="20260120160000 +0800" stop="20260120180000 +0800">
    <title lang="zh">卫星直播:2026 澳大利亚网球公开赛 男单第一轮:辛纳-加斯东</title>
  </programme>
  <programme channel="五星体育" start="20260120180000 +0800" stop="20260120190000 +0800">
    <title lang="zh">弈棋耍大牌</title>
  </programme>
  <programme channel="五星体育" start="20260120190000 +0800" stop="20260120193000 +0800">
    <title lang="zh">2026极速终点线1</title>
  </programme>
  <programme channel="五星体育" start="20260120193000 +0800" stop="20260120200000 +0800">
    <title lang="zh">体育新闻</title>
  </programme>
  <programme channel="五星体育" start="20260120200000 +0800" stop="20260120205100 +0800">
    <title lang="zh">2025SVS光明随心订虚拟自行车联赛冠军杯淘汰赛B组</title>
  </programme>
  <programme channel="五星体育" start="20260120205100 +0800" stop="20260120215500 +0800">
    <title lang="zh">2025-26赛季NBA常规赛:森林狼-火箭</title>
  </programme>
  <programme channel="五星体育" start="20260120215500 +0800" stop="20260120220000 +0800">
    <title lang="zh">健身时代 精选周二</title>
  </programme>
  <programme channel="五星体育" start="20260120220000 +0800" stop="20260120225700 +0800">
    <title lang="zh">弈棋耍大牌 -上海三打一</title>
  </programme>
  <programme channel="五星体育" start="20260120225700 +0800" stop="20260120235200 +0800">
    <title lang="zh">2026 澳大利亚网球公开赛 女单第一轮袁悦-斯瓦泰克</title>
  </programme>
  <programme channel="五星体育" start="20260120235200 +0800" stop="20260121003700 +0800">
    <title lang="zh">2025SVS光明随心订虚拟自行车联赛冠军杯淘汰赛B组</title>
  </programme>
  <programme channel="五星体育" start="20260121003700 +0800" stop="20260121013200 +0800">
    <title lang="zh">2025-26赛季NBA杯小组赛:独行侠-湖人</title>
  </programme>
  <programme channel="五星体育" start="20260121013200 +0800" stop="20260121025700 +0800">
    <title lang="zh">2025世界 斯诺克上海大师赛 决赛上:卡特-威尔逊</title>
  </programme>
  <programme channel="五星体育" start="20260121025700 +0800" stop="20260121032700 +0800">
    <title lang="zh">2025MXGP国际摩托车越野锦标赛中国上海站上午场</title>
  </programme>
  <programme channel="五星体育" start="20260121032700 +0800" stop="20260121042200 +0800">
    <title lang="zh">2025巴黎网球大师赛半决赛:兹维列夫-辛纳</title>
  </programme>
  <programme channel="五星体育" start="20260121042200 +0800" stop="20260121051400 +0800">
    <title lang="zh">2024-25 国际帆船大奖赛 英国站</title>
  </programme>
  <programme channel="五星体育" start="20260121051400 +0800" stop="20260121060400 +0800">
    <title lang="zh">2025 中超联赛 第15轮:上海海港-大连英博</title>
  </programme>
  <programme channel="五星体育" start="20260121060400 +0800" stop="20260121063000 +0800">
    <title lang="zh">2025极速终点线12</title>
  </programme>
  <programme channel="五星体育" start="20260121063000 +0800" stop="20260121072700 +0800">
    <title lang="zh">2025别克LPGA锦标赛第三比赛日</title>
  </programme>
  <programme channel="五星体育" start="20260121072700 +0800" stop="20260121082500 +0800">
    <title lang="zh">第十五届 全国运动会 赛艇决赛</title>
  </programme>
  <programme channel="五星体育" start="20260121082500 +0800" stop="20260121085600 +0800">
    <title lang="zh">2025第十五届全国运动会 乒乓球男单半决赛 :王楚钦-樊振东</title>
  </programme>
  <programme channel="五星体育" start="20260121085600 +0800" stop="20260121095500 +0800">
    <title lang="zh">2025伦敦马拉松</title>
  </programme>
  <programme channel="五星体育" start="20260121095500 +0800" stop="20260121100000 +0800">
    <title lang="zh">健身时代 精选周三</title>
  </programme>
  <programme channel="五星体育" start="20260121100000 +0800" stop="20260121105700 +0800">
    <title lang="zh">弈棋耍大牌 -上海三打一</title>
  </programme>
  <programme channel="五星体育" start="20260121105700 +0800" stop="20260121120000 +0800">
    <title lang="zh">弈棋耍大牌</title>
  </programme>
  <programme channel="五星体育" start="20260121120000 +0800" stop="20260121120500 +0800">
    <title lang="zh">健身时代 精选周三</title>
  </programme>
  <programme channel="五星体育" start="20260121120500 +0800" stop="20260121123500 +0800">
    <title lang="zh">2025第十五届全国运动会 乒乓球男单半决赛 :王楚钦-樊振东</title>
  </programme>
  <programme channel="五星体育" start="20260121123500 +0800" stop="20260121140000 +0800">
    <title lang="zh">卫星直播:2026 澳大利亚网球公开赛</title>
  </programme>
  <programme channel="五星体育" start="20260121140000 +0800" stop="20260121140500 +0800">
    <title lang="zh">健身时代 精选周三</title>
  </programme>
  <programme channel="五星体育" start="20260121140500 +0800" stop="20260121170000 +0800">
    <title lang="zh">卫星直播:2026 澳大利亚网球公开赛</title>
  </programme>
  <programme channel="五星体育" start="20260121170000 +0800" stop="20260121180000 +0800">
    <title lang="zh">五星精彩- 弈棋耍大牌 精彩牌局</title>
  </programme>
  <programme channel="五星体育" start="20260121180000 +0800" stop="20260121190000 +0800">
    <title lang="zh">弈棋耍大牌</title>
  </programme>
  <programme channel="五星体育" start="20260121190000 +0800" stop="20260121193000 +0800">
    <title lang="zh">体育新闻</title>
  </programme>
  <programme channel="五星体育" start="20260121193000 +0800" stop="20260121205200 +0800">
    <title lang="zh">2025metaSVS长三角青少年旱雪气垫大跳台公开赛</title>
  </programme>
  <programme channel="五星体育" start="20260121205200 +0800" stop="20260121215200 +0800">
    <title lang="zh">2025-26赛季NFL外卡赛:洛杉矶公羊-芝加哥熊</title>
  </programme>
  <programme channel="五星体育" start="20260121215200 +0800" stop="20260121220000 +0800">
    <title lang="zh">健身时代 精选周三</title>
  </programme>
  <programme channel="五星体育" start="20260121220000 +0800" stop="20260121225700 +0800">
    <title lang="zh">弈棋耍大牌 -上海三打一</title>
  </programme>
  <programme channel="五星体育" start="20260121225700 +0800" stop="20260121235200 +0800">
    <title lang="zh">2026 澳大利亚网球公开赛 女单第一轮:张帅-普雷斯顿</title>
  </programme>
  <programme channel="五星体育" start="20260121235200 +0800" stop="20260122004700 +0800">
    <title lang="zh">2026 澳大利亚网球公开赛 女单第一轮:王欣瑜-卡利尼娜</title>
  </programme>
  <programme channel="五星体育" start="20260122004700 +0800" stop="20260122014200 +0800">
    <title lang="zh">2026 澳大利亚网球公开赛 男单第一轮:吴易昺-纳尔迪</title>
  </programme>
  <programme channel="五星体育" start="20260122014200 +0800" stop="20260122023400 +0800">
    <title lang="zh">2025SVS光明随心订虚拟自行车联赛冠军杯决赛</title>
  </programme>
  <programme channel="五星体育" start="20260122023400 +0800" stop="20260122035900 +0800">
    <title lang="zh">2025世界 斯诺克上海大师赛 决赛下:卡特-威尔逊</title>
  </programme>
  <programme channel="五星体育" start="20260122035900 +0800" stop="20260122042900 +0800">
    <title lang="zh">2025MXGP国际摩托车越野锦标赛中国上海站下午场1</title>
  </programme>
  <programme channel="五星体育" start="20260122042900 +0800" stop="20260122052100 +0800">
    <title lang="zh">2024-25 国际帆船大奖赛 德国站</title>
  </programme>
  <programme channel="五星体育" start="20260122052100 +0800" stop="20260122060400 +0800">
    <title lang="zh">2025 中超联赛 第16轮:长春亚泰-上海申花</title>
  </programme>
  <programme channel="五星体育" start="20260122060400 +0800" stop="20260122063000 +0800">
    <title lang="zh">2025极速终点线13</title>
  </programme>
  <programme channel="五星体育" start="20260122063000 +0800" stop="20260122072700 +0800">
    <title lang="zh">2025别克LPGA锦标赛决赛日</title>
  </programme>
  <programme channel="五星体育" start="20260122072700 +0800" stop="20260122081900 +0800">
    <title lang="zh">第十五届 全国运动会 女子10米跳台决赛</title>
  </programme>
  <programme channel="五星体育" start="20260122081900 +0800" stop="20260122084900 +0800">
    <title lang="zh">2025第十五届 全国运动会 乒乓球男单决赛:林诗栋-樊振东</title>
  </programme>
  <programme channel="五星体育" start="20260122084900 +0800" stop="20260122095500 +0800">
    <title lang="zh">2025 悉尼马拉松</title>
  </programme>
  <programme channel="五星体育" start="20260122095500 +0800" stop="20260122100000 +0800">
    <title lang="zh">健身时代 精选周四</title>
  </programme>
  <programme channel="五星体育" start="20260122100000 +0800" stop="20260122105700 +0800">
    <title lang="zh">弈棋耍大牌 -上海三打一</title>
  </programme>
  <programme channel="五星体育" start="20260122105700 +0800" stop="20260122120000 +0800">
    <title lang="zh">弈棋耍大牌</title>
  </programme>
  <programme channel="五星体育" start="20260122120000 +0800" stop="20260122120500 +0800">
    <title lang="zh">健身时代 精选周四</title>
  </programme>
  <programme channel="五星体育" start="20260122120500 +0800" stop="20260122123500 +0800">
    <title lang="zh">2025第十五届 全国运动会 乒乓球男单决赛:林诗栋-樊振东</title>
  </programme>
  <programme channel="五星体育" start="20260122123500 +0800" stop="20260122140000 +0800">
    <title lang="zh">卫星直播:2026 澳大利亚网球公开赛</title>
  </programme>
  <programme channel="五星体育" start="20260122140000 +0800" stop="20260122140500 +0800">
    <title lang="zh">健身时代 精选周四</title>
  </programme>
  <programme channel="五星体育" start="20260122140500 +0800" stop="20260122170000 +0800">
    <title lang="zh">卫星直播:2026 澳大利亚网球公开赛</title>
  </programme>
  <programme channel="五星体育" start="20260122170000 +0800" stop="20260122180000 +0800">
    <title lang="zh">五星精彩- 弈棋耍大牌 精彩牌局</title>
  </programme>
  <programme channel="五星体育" start="20260122180000 +0800" stop="20260122190000 +0800">
    <title lang="zh">弈棋耍大牌</title>
  </programme>
  <programme channel="五星体育" start="20260122190000 +0800" stop="20260122193000 +0800">
    <title lang="zh">体育新闻</title>
  </programme>
  <programme channel="五星体育" start="20260122193000 +0800" stop="20260122210100 +0800">
    <title lang="zh">2025 世界一级方程式锦标赛 阿塞拜疆站大奖赛</title>
  </programme>
  <programme channel="五星体育" start="20260122210100 +0800" stop="20260122215500 +0800">
    <title lang="zh">2025 悉尼马拉松</title>
  </programme>
  <programme channel="五星体育" start="20260122215500 +0800" stop="20260122220000 +0800">
    <title lang="zh">健身时代 精选周四</title>
  </programme>
  <programme channel="五星体育" start="20260122220000 +0800" stop="20260122225700 +0800">
    <title lang="zh">弈棋耍大牌 -上海三打一</title>
  </programme>
  <programme channel="五星体育" start="20260122225700 +0800" stop="20260122235200 +0800">
    <title lang="zh">2026 澳大利亚网球公开赛</title>
  </programme>
  <programme channel="五星体育" start="20260122235200 +0800" stop="20260123002200 +0800">
    <title lang="zh">2025-26赛季NFL常规赛:纽约巨人-新英格兰爱国者</title>
  </programme>
  <channel id="欢笑剧场">
    <display-name lang="zh">欢笑剧场</display-name>
  </channel>
  <programme channel="欢笑剧场" start="20260120001100 +0800" stop="20260120001400 +0800">
    <title lang="zh">美食驾到(92):京包菜豌豆</title>
  </programme>
  <programme channel="欢笑剧场" start="20260120001400 +0800" stop="20260120001700 +0800">
    <title lang="zh">美食驾到(97):蔬菜鸡排</title>
  </programme>
  <programme channel="欢笑剧场" start="20260120001700 +0800" stop="20260120002100 +0800">
    <title lang="zh">美食驾到(100):粉丝鲶鱼排</title>
  </programme>
  <programme channel="欢笑剧场" start="20260120002100 +0800" stop="20260120002400 +0800">
    <title lang="zh">美食驾到(98):蒸粗麦粉炒蔬菜</title>
  </programme>
  <programme channel="欢笑剧场" start="20260120002400 +0800" stop="20260120002700 +0800">
    <title lang="zh">美食驾到(99):韩式萝卜沙拉</title>
  </programme>
  <programme channel="欢笑剧场" start="20260120002700 +0800" stop="20260120003000 +0800">
    <title lang="zh">冰岛风光</title>
  </programme>
  <programme channel="欢笑剧场" start="20260120003000 +0800" stop="20260120055900 +0800">
    <title lang="zh">电视播控中心播出结束</title>
  </programme>
  <programme channel="欢笑剧场" start="20260120055900 +0800" stop="20260120060000 +0800">
    <title lang="zh">电视播控中心播出开始</title>
  </programme>
  <programme channel="欢笑剧场" start="20260120060000 +0800" stop="20260120063100 +0800">
    <title lang="zh">国厨来了1(4):山珍</title>
  </programme>
  <programme channel="欢笑剧场" start="20260120063100 +0800" stop="20260120071600 +0800">
    <title lang="zh">两个人的世界(9)</title>
  </programme>
  <programme channel="欢笑剧场" start="20260120071600 +0800" stop="20260120080800 +0800">
    <title lang="zh">两个人的世界(10)</title>
  </programme>
  <programme channel="欢笑剧场" start="20260120080800 +0800" stop="20260120092000 +0800">
    <title lang="zh">2025匹克球明星巡回表演赛精华版</title>
  </programme>
  <programme channel="欢笑剧场" start="20260120092000 +0800" stop="20260120095000 +0800">
    <title lang="zh">一起烘焙吧1(3):梦龙卷</title>
  </programme>
  <programme channel="欢笑剧场" start="20260120095000 +0800" stop="20260120101800 +0800">
    <title lang="zh">一起烘焙吧1(4):翻糖蛋糕</title>
  </programme>
  <programme channel="欢笑剧场" start="20260120101800 +0800" stop="20260120123100 +0800">
    <title lang="zh">艺术大厅</title>
  </programme>
  <programme channel="欢笑剧场" start="20260120123100 +0800" stop="20260120135500 +0800">
    <title lang="zh">江南</title>
  </programme>
  <programme channel="欢笑剧场" start="20260120135500 +0800" stop="20260120142400 +0800">
    <title lang="zh">健身私享课1(17):哑铃肩部塑形</title>
  </programme>
  <programme channel="欢笑剧场" start="20260120142400 +0800" stop="20260120145300 +0800">
    <title lang="zh">健身私享课1(18):哑铃胸部塑形</title>
  </programme>
  <programme channel="欢笑剧场" start="20260120145300 +0800" stop="20260120152000 +0800">
    <title lang="zh">历史现场:浙闽廊桥</title>
  </programme>
  <programme channel="欢笑剧场" start="20260120152000 +0800" stop="20260120160400 +0800">
    <title lang="zh">两个人的世界(11)</title>
  </programme>
  <programme channel="欢笑剧场" start="20260120160400 +0800" stop="20260120164900 +0800">
    <title lang="zh">两个人的世界(12)</title>
  </programme>
  <programme channel="欢笑剧场" start="20260120164900 +0800" stop="20260120190000 +0800">
    <title lang="zh">艺术大厅:京剧</title>
  </programme>
  <programme channel="欢笑剧场" start="20260120190000 +0800" stop="20260120192900 +0800">
    <title lang="zh">健身私享课1(19):全身拉伸</title>
  </programme>
  <programme channel="欢笑剧场" start="20260120192900 +0800" stop="20260120200000 +0800">
    <title lang="zh">健身私享课1:徒手全身训练入门</title>
  </programme>
  <programme channel="欢笑剧场" start="20260120200000 +0800" stop="20260120203500 +0800">
    <title lang="zh">历史现场:松江城市露天博物馆</title>
  </programme>
  <programme channel="欢笑剧场" start="20260120203500 +0800" stop="20260120212000 +0800">
    <title lang="zh">两个人的世界(13)</title>
  </programme>
  <programme channel="欢笑剧场" start="20260120212000 +0800" stop="20260120220500 +0800">
    <title lang="zh">两个人的世界(14)</title>
  </programme>
  <programme channel="欢笑剧场" start="20260120220500 +0800" stop="20260120002600 +0800">
    <title lang="zh">艺术大厅:京剧</title>
  </programme>
  <channel id="生活时尚">
    <display-name lang="zh">生活时尚</display-name>
  </channel>
  <programme channel="生活时尚" start="20260120002000 +0800" stop="20260120002100 +0800">
    <title lang="zh">一碗人间烟火(21):黑松露炒虾球</title>
  </programme>
  <programme channel="生活时尚" start="20260120002100 +0800" stop="20260120002400 +0800">
    <title lang="zh">闲着:七宝茶馆</title>
  </programme>
  <programme channel="生活时尚" start="20260120002400 +0800" stop="20260120002800 +0800">
    <title lang="zh">漫步上海:松江城市露天博物馆</title>
  </programme>
  <programme channel="生活时尚" start="20260120002800 +0800" stop="20260120003000 +0800">
    <title lang="zh">自然之旅欣赏</title>
  </programme>
  <programme channel="生活时尚" start="20260120003000 +0800" stop="20260120055900 +0800">
    <title lang="zh">电视播控中心播出结束</title>
  </programme>
  <programme channel="生活时尚" start="20260120055900 +0800" stop="20260120060000 +0800">
    <title lang="zh">电视播控中心播出开始</title>
  </programme>
  <programme channel="生活时尚" start="20260120060000 +0800" stop="20260120062900 +0800">
    <title lang="zh">原味记忆:无锡小吃</title>
  </programme>
  <programme channel="生活时尚" start="20260120062900 +0800" stop="20260120064900 +0800">
    <title lang="zh">大医来了</title>
  </programme>
  <programme channel="生活时尚" start="20260120064900 +0800" stop="20260120065300 +0800">
    <title lang="zh">闲着:名厨本帮馆</title>
  </programme>
  <programme channel="生活时尚" start="20260120065300 +0800" stop="20260120065600 +0800">
    <title lang="zh">一碗人间烟火:春菜烩小黄鱼卷</title>
  </programme>
  <programme channel="生活时尚" start="20260120065600 +0800" stop="20260120070000 +0800">
    <title lang="zh">日食记:香菜牛肉凉面</title>
  </programme>
  <programme channel="生活时尚" start="20260120070000 +0800" stop="20260120070100 +0800">
    <title lang="zh">荧屏之星新春版(1)</title>
  </programme>
  <programme channel="生活时尚" start="20260120070100 +0800" stop="20260120072100 +0800">
    <title lang="zh">加油!宠星人1(12)</title>
  </programme>
  <programme channel="生活时尚" start="20260120072100 +0800" stop="20260120072400 +0800">
    <title lang="zh">漫步上海(28):杨浦滨江生态之旅</title>
  </programme>
  <programme channel="生活时尚" start="20260120072400 +0800" stop="20260120073000 +0800">
    <title lang="zh">徐汇阅读建筑(3)</title>
  </programme>
  <programme channel="生活时尚" start="20260120073000 +0800" stop="20260120082000 +0800">
    <title lang="zh">万物滋养(5):江湖里的追逐</title>
  </programme>
  <programme channel="生活时尚" start="20260120082000 +0800" stop="20260120085000 +0800">
    <title lang="zh">原味记忆:陕西小吃(下)</title>
  </programme>
  <programme channel="生活时尚" start="20260120085000 +0800" stop="20260120090500 +0800">
    <title lang="zh">金色公开课:声音嘶哑,故事课</title>
  </programme>
  <programme channel="生活时尚" start="20260120090500 +0800" stop="20260120090700 +0800">
    <title lang="zh">一碗人间烟火(21):黑松露炒虾球</title>
  </programme>
  <programme channel="生活时尚" start="20260120090700 +0800" stop="20260120091000 +0800">
    <title lang="zh">闲着:七宝茶馆</title>
  </programme>
  <programme channel="生活时尚" start="20260120091000 +0800" stop="20260120091400 +0800">
    <title lang="zh">漫步上海:松江城市露天博物馆</title>
  </programme>
  <programme channel="生活时尚" start="20260120091400 +0800" stop="20260120091500 +0800">
    <title lang="zh">荧屏之星新春版(1)</title>
  </programme>
  <programme channel="生活时尚" start="20260120091500 +0800" stop="20260120092100 +0800">
    <title lang="zh">时尚日志(71)</title>
  </programme>
  <programme channel="生活时尚" start="20260120092100 +0800" stop="20260120094100 +0800">
    <title lang="zh">加油!宠星人1:智商担当牧羊犬</title>
  </programme>
  <programme channel="生活时尚" start="20260120094100 +0800" stop="20260120094600 +0800">
    <title lang="zh">徐汇阅读建筑:梧桐树下的爱国心</title>
  </programme>
  <programme channel="生活时尚" start="20260120094600 +0800" stop="20260120095000 +0800">
    <title lang="zh">日食记:鲜虾豆腐煲</title>
  </programme>
  <programme channel="生活时尚" start="20260120095000 +0800" stop="20260120104000 +0800">
    <title lang="zh">万物滋养(4):田野中的冒险</title>
  </programme>
  <programme channel="生活时尚" start="20260120104000 +0800" stop="20260120111000 +0800">
    <title lang="zh">原味记忆:无锡小吃</title>
  </programme>
  <programme channel="生活时尚" start="20260120111000 +0800" stop="20260120113000 +0800">
    <title lang="zh">大医来了</title>
  </programme>
  <programme channel="生活时尚" start="20260120113000 +0800" stop="20260120113300 +0800">
    <title lang="zh">闲着:名厨本帮馆</title>
  </programme>
  <programme channel="生活时尚" start="20260120113300 +0800" stop="20260120113700 +0800">
    <title lang="zh">一碗人间烟火:春菜烩小黄鱼卷</title>
  </programme>
  <programme channel="生活时尚" start="20260120113700 +0800" stop="20260120114100 +0800">
    <title lang="zh">日食记:香菜牛肉凉面</title>
  </programme>
  <programme channel="生活时尚" start="20260120114100 +0800" stop="20260120114200 +0800">
    <title lang="zh">荧屏之星新春版(1)</title>
  </programme>
  <programme channel="生活时尚" start="20260120114200 +0800" stop="20260120120200 +0800">
    <title lang="zh">加油!宠星人1(12)</title>
  </programme>
  <programme channel="生活时尚" start="20260120120200 +0800" stop="20260120120500 +0800">
    <title lang="zh">漫步上海(28):杨浦滨江生态之旅</title>
  </programme>
  <programme channel="生活时尚" start="20260120120500 +0800" stop="20260120121000 +0800">
    <title lang="zh">徐汇阅读建筑(3)</title>
  </programme>
  <programme channel="生活时尚" start="20260120121000 +0800" stop="20260120130100 +0800">
    <title lang="zh">万物滋养(5):江湖里的追逐</title>
  </programme>
  <programme channel="生活时尚" start="20260120130100 +0800" stop="20260120133100 +0800">
    <title lang="zh">原味记忆:陕西小吃(下)</title>
  </programme>
  <programme channel="生活时尚" start="20260120133100 +0800" stop="20260120134600 +0800">
    <title lang="zh">金色公开课:声音嘶哑,故事课</title>
  </programme>
  <programme channel="生活时尚" start="20260120134600 +0800" stop="20260120134800 +0800">
    <title lang="zh">一碗人间烟火(21):黑松露炒虾球</title>
  </programme>
  <programme channel="生活时尚" start="20260120134800 +0800" stop="20260120135100 +0800">
    <title lang="zh">闲着:七宝茶馆</title>
  </programme>
  <programme channel="生活时尚" start="20260120135100 +0800" stop="20260120135500 +0800">
    <title lang="zh">漫步上海:松江城市露天博物馆</title>
  </programme>
  <programme channel="生活时尚" start="20260120135500 +0800" stop="20260120135600 +0800">
    <title lang="zh">荧屏之星新春版(1)</title>
  </programme>
  <programme channel="生活时尚" start="20260120135600 +0800" stop="20260120140100 +0800">
    <title lang="zh">时尚日志(71)</title>
  </programme>
  <programme channel="生活时尚" start="20260120140100 +0800" stop="20260120142100 +0800">
    <title lang="zh">加油!宠星人1:智商担当牧羊犬</title>
  </programme>
  <programme channel="生活时尚" start="20260120142100 +0800" stop="20260120142700 +0800">
    <title lang="zh">徐汇阅读建筑:梧桐树下的爱国心</title>
  </programme>
  <programme channel="生活时尚" start="20260120142700 +0800" stop="20260120143100 +0800">
    <title lang="zh">日食记:鲜虾豆腐煲</title>
  </programme>
  <programme channel="生活时尚" start="20260120143100 +0800" stop="20260120152100 +0800">
    <title lang="zh">万物滋养(4):田野中的冒险</title>
  </programme>
  <programme channel="生活时尚" start="20260120152100 +0800" stop="20260120155100 +0800">
    <title lang="zh">原味记忆:无锡小吃</title>
  </programme>
  <programme channel="生活时尚" start="20260120155100 +0800" stop="20260120161100 +0800">
    <title lang="zh">大医来了</title>
  </programme>
  <programme channel="生活时尚" start="20260120161100 +0800" stop="20260120161400 +0800">
    <title lang="zh">闲着:名厨本帮馆</title>
  </programme>
  <programme channel="生活时尚" start="20260120161400 +0800" stop="20260120161700 +0800">
    <title lang="zh">一碗人间烟火:春菜烩小黄鱼卷</title>
  </programme>
  <programme channel="生活时尚" start="20260120161700 +0800" stop="20260120162200 +0800">
    <title lang="zh">日食记:香菜牛肉凉面</title>
  </programme>
  <programme channel="生活时尚" start="20260120162200 +0800" stop="20260120162300 +0800">
    <title lang="zh">荧屏之星新春版(1)</title>
  </programme>
  <programme channel="生活时尚" start="20260120162300 +0800" stop="20260120164300 +0800">
    <title lang="zh">加油!宠星人1(12)</title>
  </programme>
  <programme channel="生活时尚" start="20260120164300 +0800" stop="20260120164500 +0800">
    <title lang="zh">漫步上海(28):杨浦滨江生态之旅</title>
  </programme>
  <programme channel="生活时尚" start="20260120164500 +0800" stop="20260120165100 +0800">
    <title lang="zh">徐汇阅读建筑(3)</title>
  </programme>
  <programme channel="生活时尚" start="20260120165100 +0800" stop="20260120174200 +0800">
    <title lang="zh">万物滋养(5):江湖里的追逐</title>
  </programme>
  <programme channel="生活时尚" start="20260120174200 +0800" stop="20260120181200 +0800">
    <title lang="zh">原味记忆:陕西小吃(下)</title>
  </programme>
  <programme channel="生活时尚" start="20260120181200 +0800" stop="20260120182700 +0800">
    <title lang="zh">金色公开课:声音嘶哑,故事课</title>
  </programme>
  <programme channel="生活时尚" start="20260120182700 +0800" stop="20260120182800 +0800">
    <title lang="zh">一碗人间烟火(21):黑松露炒虾球</title>
  </programme>
  <programme channel="生活时尚" start="20260120182800 +0800" stop="20260120183100 +0800">
    <title lang="zh">闲着:七宝茶馆</title>
  </programme>
  <programme channel="生活时尚" start="20260120183100 +0800" stop="20260120183200 +0800">
    <title lang="zh">荧屏之星新春版(1)</title>
  </programme>
  <programme channel="生活时尚" start="20260120183200 +0800" stop="20260120183700 +0800">
    <title lang="zh">时尚日志(71)</title>
  </programme>
  <programme channel="生活时尚" start="20260120183700 +0800" stop="20260120184000 +0800">
    <title lang="zh">日食记:鲜虾豆腐煲</title>
  </programme>
  <programme channel="生活时尚" start="20260120184000 +0800" stop="20260120193000 +0800">
    <title lang="zh">万物滋养(4):田野中的冒险</title>
  </programme>
  <programme channel="生活时尚" start="20260120193000 +0800" stop="20260120195800 +0800">
    <title lang="zh">原味记忆:重庆小吃</title>
  </programme>
  <programme channel="生活时尚" start="20260120195800 +0800" stop="20260120200000 +0800">
    <title lang="zh">荧屏之星新春版(1)</title>
  </programme>
  <programme channel="生活时尚" start="20260120200000 +0800" stop="20260120202000 +0800">
    <title lang="zh">大医来了:消化道早癌镜界革命</title>
  </programme>
  <programme channel="生活时尚" start="20260120202000 +0800" stop="20260120202400 +0800">
    <title lang="zh">闲着:浅烘咖啡</title>
  </programme>
  <programme channel="生活时尚" start="20260120202400 +0800" stop="20260120202900 +0800">
    <title lang="zh">日食记:自制酱料</title>
  </programme>
  <programme channel="生活时尚" start="20260120202900 +0800" stop="20260120203000 +0800">
    <title lang="zh">荧屏之星新春版(1)</title>
  </programme>
  <programme channel="生活时尚" start="20260120203000 +0800" stop="20260120210000 +0800">
    <title lang="zh">健身私享课2(19):跃动燃脂强化</title>
  </programme>
  <programme channel="生活时尚" start="20260120210000 +0800" stop="20260120213000 +0800">
    <title lang="zh">健康生活</title>
  </programme>
  <programme channel="生活时尚" start="20260120213000 +0800" stop="20260120215000 +0800">
    <title lang="zh">加油!宠星人1(13)</title>
  </programme>
  <programme channel="生活时尚" start="20260120215000 +0800" stop="20260120215300 +0800">
    <title lang="zh">一碗人间烟火:春笋年糕白鲳鱼</title>
  </programme>
  <programme channel="生活时尚" start="20260120215300 +0800" stop="20260120215600 +0800">
    <title lang="zh">漫步上海(15):上海音乐学院</title>
  </programme>
  <programme channel="生活时尚" start="20260120215600 +0800" stop="20260120220000 +0800">
    <title lang="zh">此心安处是吾乡</title>
  </programme>
  <programme channel="生活时尚" start="20260120220000 +0800" stop="20260120225100 +0800">
    <title lang="zh">万物滋养(6):高原上的温存</title>
  </programme>
  <programme channel="生活时尚" start="20260120225100 +0800" stop="20260120231800 +0800">
    <title lang="zh">原味记忆:重庆小吃</title>
  </programme>
  <programme channel="生活时尚" start="20260120231800 +0800" stop="20260120232000 +0800">
    <title lang="zh">荧屏之星新春版(1)</title>
  </programme>
  <programme channel="生活时尚" start="20260120232000 +0800" stop="20260120234000 +0800">
    <title lang="zh">大医来了:消化道早癌镜界革命</title>
  </programme>
  <programme channel="生活时尚" start="20260120234000 +0800" stop="20260120234400 +0800">
    <title lang="zh">闲着:浅烘咖啡</title>
  </programme>
  <programme channel="生活时尚" start="20260120234400 +0800" stop="20260120235100 +0800">
    <title lang="zh">日食记:自制酱料</title>
  </programme>
  <programme channel="生活时尚" start="20260120235100 +0800" stop="20260120235900 +0800">
    <title lang="zh">健身私享课2(19):跃动燃脂强化</title>
  </programme>
  <programme channel="生活时尚" start="20260120235900 +0800" stop="20260120002000 +0800">
    <title lang="zh">结束</title>
  </programme>
  <channel id="都市剧场">
    <display-name lang="zh">都市剧场</display-name>
  </channel>
  <programme channel="都市剧场" start="20260120001700 +0800" stop="20260120002200 +0800">
    <title lang="zh">精彩赏析:黎明决战(1)</title>
  </programme>
  <programme channel="都市剧场" start="20260120002200 +0800" stop="20260120003000 +0800">
    <title lang="zh">精彩赏析:我在北京挺好的(2)</title>
  </programme>
  <programme channel="都市剧场" start="20260120003000 +0800" stop="20260120055900 +0800">
    <title lang="zh">电视播控中心播出结束</title>
  </programme>
  <programme channel="都市剧场" start="20260120055900 +0800" stop="20260120060100 +0800">
    <title lang="zh">电视播控中心播出开始</title>
  </programme>
  <programme channel="都市剧场" start="20260120060100 +0800" stop="20260120064200 +0800">
    <title lang="zh">独狼(3)</title>
  </programme>
  <programme channel="都市剧场" start="20260120064200 +0800" stop="20260120065000 +0800">
    <title lang="zh">精彩赏析:老男孩(5)</title>
  </programme>
  <programme channel="都市剧场" start="20260120065000 +0800" stop="20260120073200 +0800">
    <title lang="zh">前途无量(8)</title>
  </programme>
  <programme channel="都市剧场" start="20260120073200 +0800" stop="20260120081300 +0800">
    <title lang="zh">前途无量(9)</title>
  </programme>
  <programme channel="都市剧场" start="20260120081300 +0800" stop="20260120085800 +0800">
    <title lang="zh">前途无量(10)</title>
  </programme>
  <programme channel="都市剧场" start="20260120085800 +0800" stop="20260120090300 +0800">
    <title lang="zh">精彩赏析:甜蜜(1)</title>
  </programme>
  <programme channel="都市剧场" start="20260120090300 +0800" stop="20260120090800 +0800">
    <title lang="zh">精彩赏析:漂洋过海来看你(1)</title>
  </programme>
  <programme channel="都市剧场" start="20260120090800 +0800" stop="20260120091700 +0800">
    <title lang="zh">精彩赏析:棋逢对手(3)</title>
  </programme>
  <programme channel="都市剧场" start="20260120091700 +0800" stop="20260120093100 +0800">
    <title lang="zh">精彩赏析:护宝风云(3)</title>
  </programme>
  <programme channel="都市剧场" start="20260120093100 +0800" stop="20260120101200 +0800">
    <title lang="zh">独狼(4)</title>
  </programme>
  <programme channel="都市剧场" start="20260120101200 +0800" stop="20260120105200 +0800">
    <title lang="zh">独狼(5)</title>
  </programme>
  <programme channel="都市剧场" start="20260120105200 +0800" stop="20260120113300 +0800">
    <title lang="zh">独狼(6)</title>
  </programme>
  <programme channel="都市剧场" start="20260120113300 +0800" stop="20260120121400 +0800">
    <title lang="zh">独狼(7)</title>
  </programme>
  <programme channel="都市剧场" start="20260120121400 +0800" stop="20260120125800 +0800">
    <title lang="zh">独狼(8)</title>
  </programme>
  <programme channel="都市剧场" start="20260120125800 +0800" stop="20260120130200 +0800">
    <title lang="zh">精彩赏析:午夜蝴蝶(1)</title>
  </programme>
  <programme channel="都市剧场" start="20260120130200 +0800" stop="20260120130800 +0800">
    <title lang="zh">精彩赏析:一马三司令(2)</title>
  </programme>
  <programme channel="都市剧场" start="20260120130800 +0800" stop="20260120131800 +0800">
    <title lang="zh">精彩赏析:一马换三羊(3)</title>
  </programme>
  <programme channel="都市剧场" start="20260120131800 +0800" stop="20260120133000 +0800">
    <title lang="zh">精彩赏析:爱的追踪(4)</title>
  </programme>
  <programme channel="都市剧场" start="20260120133000 +0800" stop="20260120141200 +0800">
    <title lang="zh">前途无量(11)</title>
  </programme>
  <programme channel="都市剧场" start="20260120141200 +0800" stop="20260120145300 +0800">
    <title lang="zh">前途无量(12)</title>
  </programme>
  <programme channel="都市剧场" start="20260120145300 +0800" stop="20260120153600 +0800">
    <title lang="zh">前途无量(13)</title>
  </programme>
  <programme channel="都市剧场" start="20260120153600 +0800" stop="20260120154600 +0800">
    <title lang="zh">精彩赏析:老男孩(2)</title>
  </programme>
  <programme channel="都市剧场" start="20260120154600 +0800" stop="20260120162700 +0800">
    <title lang="zh">独狼(9)</title>
  </programme>
  <programme channel="都市剧场" start="20260120162700 +0800" stop="20260120170800 +0800">
    <title lang="zh">独狼(10)</title>
  </programme>
  <programme channel="都市剧场" start="20260120170800 +0800" stop="20260120174900 +0800">
    <title lang="zh">独狼(11)</title>
  </programme>
  <programme channel="都市剧场" start="20260120174900 +0800" stop="20260120183000 +0800">
    <title lang="zh">独狼(12)</title>
  </programme>
  <programme channel="都市剧场" start="20260120183000 +0800" stop="20260120191100 +0800">
    <title lang="zh">独狼(13)</title>
  </programme>
  <programme channel="都市剧场" start="20260120191100 +0800" stop="20260120191600 +0800">
    <title lang="zh">精彩赏析:一马换三羊(2)</title>
  </programme>
  <programme channel="都市剧场" start="20260120191600 +0800" stop="20260120192000 +0800">
    <title lang="zh">精彩赏析:尖锋之烈焰青春(2)</title>
  </programme>
  <programme channel="都市剧场" start="20260120192000 +0800" stop="20260120192500 +0800">
    <title lang="zh">精彩赏析:宜昌保卫战(3)</title>
  </programme>
  <programme channel="都市剧场" start="20260120192500 +0800" stop="20260120200700 +0800">
    <title lang="zh">前途无量(14)</title>
  </programme>
  <programme channel="都市剧场" start="20260120200700 +0800" stop="20260120205000 +0800">
    <title lang="zh">前途无量(15)</title>
  </programme>
  <programme channel="都市剧场" start="20260120205000 +0800" stop="20260120212000 +0800">
    <title lang="zh">健康生活</title>
  </programme>
  <programme channel="都市剧场" start="20260120212000 +0800" stop="20260120220200 +0800">
    <title lang="zh">前途无量(16)</title>
  </programme>
  <programme channel="都市剧场" start="20260120220200 +0800" stop="20260120223200 +0800">
    <title lang="zh">健康生活</title>
  </programme>
  <programme channel="都市剧场" start="20260120223200 +0800" stop="20260120000900 +0800">
    <title lang="zh">暴风</title>
  </programme>
  <channel id="金鹰纪实">
    <display-name lang="zh">金鹰纪实</display-name>
  </channel>
</tv>
